{
  "glucose": [
    {
      "id": 1743894000001,
      "date": "2026-03-25",
      "time": "07:12",
      "value": 181,
      "type": "fasting",
      "notes": "Anchor — Day 1"
    },
    {
      "id": 1743894000002,
      "date": "2026-03-26",
      "time": "07:08",
      "value": 173,
      "type": "fasting",
      "notes": "Anchor — Day 2"
    },
    {
      "id": 1743894000003,
      "date": "2026-03-27",
      "time": "07:05",
      "value": 202,
      "type": "fasting",
      "notes": "Anchor — Day 3"
    },
    {
      "id": 1743894000004,
      "date": "2026-03-28",
      "time": "07:22",
      "value": 199,
      "type": "fasting",
      "notes": "Anchor — Day 4"
    },
    {
      "id": 1743894000005,
      "date": "2026-03-29",
      "time": "07:10",
      "value": 185,
      "type": "fasting",
      "notes": "Anchor — Day 5"
    },
    {
      "id": 1743894000006,
      "date": "2026-03-30",
      "time": "07:00",
      "value": 179,
      "type": "fasting",
      "notes": "Anchor — Day 6"
    },
    {
      "id": 1743894000007,
      "date": "2026-03-31",
      "time": "06:55",
      "value": 181,
      "type": "fasting",
      "notes": "Anchor — Day 7"
    },
    {
      "id": 1743894000008,
      "date": "2026-04-01",
      "time": "07:18",
      "value": 204,
      "type": "fasting",
      "notes": "Anchor — Day 8"
    },
    {
      "id": 1743894000009,
      "date": "2026-04-02",
      "time": "07:30",
      "value": 179,
      "type": "fasting",
      "notes": "Anchor — Day 9"
    },
    {
      "id": 1743894000010,
      "date": "2026-04-03",
      "time": "07:02",
      "value": 177,
      "type": "fasting",
      "notes": "Anchor — Day 10"
    },
    {
      "id": 1743894000011,
      "date": "2026-04-04",
      "time": "07:35",
      "value": 223,
      "type": "fasting",
      "notes": "Hot cocoa and the beans and rice."
    },
    {
      "id": 1743894000012,
      "date": "2026-04-05",
      "time": "07:14",
      "value": 231,
      "type": "fasting",
      "notes": "Anchor — Day 12 — Spike (Cocoa/Rice)"
    },
    {
      "id": 1743894000013,
      "date": "2026-04-06",
      "time": "06:58",
      "value": 178,
      "type": "fasting",
      "notes": "Anchor — Day 13"
    },
    {
      "id": 1743894000014,
      "date": "2026-04-07",
      "time": "07:14",
      "value": 163,
      "type": "fasting",
      "notes": "Today reading was amazing."
    },
    {
      "id": 1775737083129,
      "date": "2026-04-09",
      "time": "05:18",
      "value": 175,
      "type": "fasting",
      "notes": "Today was a good reading it could get better"
    },
    {
      "id": 1775737810345,
      "date": "2026-04-09",
      "time": "05:30",
      "value": 175,
      "type": "fasting",
      "notes": "Today was a good reading it could be better"
    },
    {
      "id": 1775824844276,
      "date": "2026-04-10",
      "time": "05:40",
      "value": 149,
      "type": "fasting",
      "notes": "Today reading was amazing🤩🫱🏾"
    },
    {
      "id": 1775995548522,
      "date": "2026-04-12",
      "time": "05:05",
      "value": 150,
      "type": "fasting",
      "notes": "Today reading was amazing🤩👋🏾"
    },
    {
      "id": 1776077347415,
      "date": "2026-04-13",
      "time": "03:49",
      "value": 156,
      "type": "fasting",
      "notes": "Today reading was amazing🤩👋🏾"
    },
    {
      "id": 1776167984073,
      "date": "2026-04-14",
      "time": "04:59",
      "value": 151,
      "type": "fasting",
      "notes": "Today reading was amazing🤩👋🏾"
    },
    {
      "id": 1776259199140,
      "date": "2026-04-15",
      "time": "06:19",
      "value": 167,
      "type": "fasting",
      "notes": "Today reading was amazing🤩👋🏾"
    },
    {
      "id": 1776339287317,
      "date": "2026-04-16",
      "time": "04:34",
      "value": 121,
      "type": "fasting",
      "notes": "Today's reading was amazing🤩👋🏾"
    },
    {
      "id": 1776599690993,
      "date": "2026-04-19",
      "time": "04:54",
      "value": 149,
      "type": "fasting",
      "notes": "Today reading was amazing.🤩👋🏾"
    },
    {
      "id": 1776706934385,
      "date": "2026-04-20",
      "time": "10:42",
      "value": 169,
      "type": "fasting",
      "notes": "Today was an amazing day 🤩👋🏾"
    },
    {
      "id": 1776774673644,
      "date": "2026-04-21",
      "time": "05:31",
      "value": 165,
      "type": "fasting",
      "notes": "Today reading was amazing.🤩👋🏾"
    },
    {
      "id": 1776880271296,
      "date": "2026-04-22",
      "time": "10:51",
      "value": 167,
      "type": "fasting",
      "notes": "Today was a great day. I'm still working on getting it lower."
    },
    {
      "id": 1776944226093,
      "date": "2026-04-23",
      "time": "04:37",
      "value": 158,
      "type": "fasting",
      "notes": "Today reading was amazing🤩👋🏾"
    },
    {
      "id": 1777031775897,
      "date": "2026-04-24",
      "time": "04:56",
      "value": 187,
      "type": "fasting",
      "notes": "I'm still working on getting it lower. I ate Philly Chicken Sandwich. A Philly cheese sandwich."
    },
    {
      "id": 1777120364186,
      "date": "2026-04-25",
      "time": "05:32",
      "value": 156,
      "type": "fasting",
      "notes": "Today reading was amazing🤩👋🏾"
    },
    {
      "id": 1777213229211,
      "date": "2026-04-26",
      "time": "07:20",
      "value": 144,
      "type": "fasting",
      "notes": "Today reading was amazing🤩👋🏾"
    },
    {
      "id": 1777289219678,
      "date": "2026-04-27",
      "time": "04:26",
      "value": 194,
      "type": "fasting",
      "notes": "I drank some Chocolate milk last night. That's why it's this high."
    },
    {
      "id": 1777375991971,
      "date": "2026-04-28",
      "time": "04:33",
      "value": 154,
      "type": "fasting",
      "notes": "Today reading was amazing🤩👋🏾"
    },
    {
      "id": 1777552168372,
      "date": "2026-04-30",
      "time": "05:29",
      "value": 146,
      "type": "fasting",
      "notes": "Today was amazing reading🤩👋🏾"
    },
    {
      "id": 1777635804495,
      "date": "2026-05-01",
      "time": "04:43",
      "value": 149,
      "type": "fasting",
      "notes": "Today reading was amazing🤩👋🏾"
    },
    {
      "id": 1777727561307,
      "date": "2026-05-02",
      "time": "06:12",
      "value": 167,
      "type": "fasting",
      "notes": "Today reading was amazing🤩👋🏾"
    },
    {
      "id": 1777813677427,
      "date": "2026-05-03",
      "time": "06:07",
      "value": 136,
      "type": "fasting",
      "notes": "today reading was amazing🤩👍🏾"
    },
    {
      "id": 1777949057075,
      "date": "2026-05-05",
      "time": "19:44",
      "value": 164,
      "type": "fasting",
      "notes": "Today reading was amazing🤩👋🏾"
    },
    {
      "id": 1777980888921,
      "date": "2026-05-05",
      "time": "04:34",
      "value": 153,
      "type": "fasting",
      "notes": "Today reading was amazing🤩👋🏾"
    },
    {
      "id": 1777982104674,
      "date": "2026-05-05",
      "time": "04:55",
      "value": 153,
      "type": "fasting",
      "notes": "Today reading was amazing🤩👋🏾"
    },
    {
      "id": 1778067056973,
      "date": "2026-05-06",
      "time": "04:30",
      "value": 139,
      "type": "fasting",
      "notes": "Today reading was amazing🤩👋🏾"
    },
    {
      "id": 1778153884503,
      "date": "2026-05-07",
      "time": "04:38",
      "value": 137,
      "type": "fasting",
      "notes": "Today rating was amazing🤩👋🏾"
    },
    {
      "id": 1778243272024,
      "date": "2026-05-08",
      "time": "05:27",
      "value": 164,
      "type": "fasting",
      "notes": "Today reading was amazing🤩👋🏾"
    },
    {
      "id": 1778647253728,
      "date": "2026-05-13",
      "time": "21:40",
      "value": 145,
      "type": "fasting",
      "notes": "Today was an amazing day🤩👋🏾"
    },
    {
      "id": 1778762593486,
      "date": "2026-05-14",
      "time": "05:43",
      "value": 170,
      "type": "fasting",
      "notes": "Today, reading was OK.🤩👋🏾"
    },
    {
      "id": 1778843385847,
      "date": "2026-05-15",
      "time": "04:09",
      "value": 146,
      "type": "fasting",
      "notes": "Today reading was amazing🤩👋🏾"
    },
    {
      "id": 1778939057617,
      "date": "2026-05-16",
      "time": "06:44",
      "value": 140,
      "type": "fasting",
      "notes": "Today was an amazing reading🤩👋🏾"
    },
    {
      "id": 1779016906022,
      "date": "2026-05-17",
      "time": "04:21",
      "value": 161,
      "type": "fasting",
      "notes": "Today reading was amazing🤩👋🏾"
    }
  ],
  "bloodPressure": [],
  "weightLog": [
    {
      "id": 1744228680001,
      "date": "2026-04-09",
      "time": "00:00",
      "value": 207,
      "notes": "Anchor — WEIGHT_ENGINE_ACTIVATE"
    }
  ],
  "weight_goal": 185,
  "last_lab_a1c": 8.6,
  "projected_a1c": 8.23,
  "lastUpdated": "2026-05-17T11:21:46.025Z",
  "glucose_target": 175
}